athena_mvsh/__init__.py
athena_mvsh/app_cli/sql.py
athena_mvsh/app_cli/version.py
athena_mvsh/cli.py
athena_mvsh/connection.py
athena_mvsh/converter.py
athena_mvsh/cursores/__init__.py
athena_mvsh/cursores/cursores.py
athena_mvsh/cursores/cursorparquet.py
athena_mvsh/cursores/cursorparquetduckdb.py
athena_mvsh/cursores/cursorpython.py
athena_mvsh/dbathena.py
athena_mvsh/error.py
athena_mvsh/formatador.py
athena_mvsh/utils.py
athena_mvsh-0.0.22.dist-info/entry_points.txt
athena_mvsh-0.0.22.dist-info/METADATA
athena_mvsh-0.0.22.dist-info/WHEEL
athena_mvsh-0.0.22.dist-info/RECORD
