Metadata-Version: 2.3
Name: athena-mvsh
Version: 0.0.22
Summary: Athena-mvsh é um biblioteca python, que interage com o serviço Amazon Athena
Author: Marcus Holanda
Author-email: mvsh777@hotmail.com
Requires-Python: >=3.9,<4.0
Classifier: Development Status :: 1 - Planning
Classifier: Natural Language :: Portuguese (Brazilian)
Classifier: Programming Language :: PL/SQL
Classifier: Programming Language :: Python :: 3
Classifier: Programming Language :: Python :: 3.9
Classifier: Programming Language :: Python :: 3.10
Classifier: Programming Language :: Python :: 3.11
Classifier: Programming Language :: Python :: 3.12
Classifier: Programming Language :: Python :: 3.13
Classifier: Topic :: Database :: Front-Ends
Provides-Extra: cli
Requires-Dist: boto3 (>=1.34.136,<2.0.0)
Requires-Dist: click (<8.2.0) ; extra == "cli"
Requires-Dist: duckdb (>=1.0.0,<2.0.0)
Requires-Dist: pandas (>=2.2.2,<3.0.0)
Requires-Dist: pyarrow (>=16,<23)
Requires-Dist: rich (>=14.0) ; extra == "cli"
Requires-Dist: textual (>=5.3.0) ; extra == "cli"
Requires-Dist: typer (>=0.15) ; extra == "cli"
Project-URL: Codigo, https://github.com/Marcus-Holanda777/athena-mvsh
Project-URL: Documentacao, https://marcus-holanda777.github.io/athena-mvsh
